nodezator/__init__.py
nodezator/__main__.py
nodezator/appinfo.py
nodezator/audioplayer.py
nodezator/config.py
nodezator/dialog.py
nodezator/hideswitch.py
nodezator/iconfactory.py
nodezator/knownpacks.py
nodezator/mainloop.py
nodezator/memoryman.py
nodezator/recentfile.py
nodezator/surfdef.py
nodezator/svgutils.py
nodezator/translation.py
nodezator/alphamask/__init__.py
nodezator/alphamask/basicop.py
nodezator/alphamask/main.py
nodezator/alphamask/masksop.py
nodezator/alphamask/utils.py
nodezator/classes2d/__init__.py
nodezator/classes2d/collections.py
nodezator/classes2d/single.py
nodezator/classes2d/surfaceswitcher.py
nodezator/colorsman/__init__.py
nodezator/colorsman/color2d.py
nodezator/colorsman/colors.py
nodezator/colorsman/editor/__init__.py
nodezator/colorsman/editor/loopop.py
nodezator/colorsman/editor/main.py
nodezator/colorsman/editor/widgetop.py
nodezator/colorsman/editor/panel/__init__.py
nodezator/colorsman/editor/panel/colorsop.py
nodezator/colorsman/editor/panel/constants.py
nodezator/colorsman/editor/panel/data.py
nodezator/colorsman/editor/panel/main.py
nodezator/colorsman/editor/widgetsetup/__init__.py
nodezator/colorsman/editor/widgetsetup/button.py
nodezator/colorsman/editor/widgetsetup/constants.py
nodezator/colorsman/editor/widgetsetup/entry.py
nodezator/colorsman/editor/widgetsetup/label.py
nodezator/colorsman/editor/widgetsetup/scale.py
nodezator/colorsman/picker/__init__.py
nodezator/colorsman/picker/constants.py
nodezator/colorsman/picker/main.py
nodezator/colorsman/picker/op.py
nodezator/colorsman/viewer/__init__.py
nodezator/colorsman/viewer/main.py
nodezator/colorsman/viewer/modes/__init__.py
nodezator/colorsman/viewer/modes/colorlist.py
nodezator/colorsman/viewer/modes/patterns/__init__.py
nodezator/colorsman/viewer/modes/patterns/main.py
nodezator/colorsman/viewer/modes/patterns/particles.py
nodezator/colorsman/viewer/modes/patterns/waves.py
nodezator/data/app_icon.png
nodezator/data/glossary.rst
nodezator-1.5.4.dist-info/METADATA
nodezator-1.5.4.dist-info/WHEEL
nodezator-1.5.4.dist-info/entry_points.txt
nodezator-1.5.4.dist-info/top_level.txt
nodezator-1.5.4.dist-info/RECORD
