Metadata-Version: 2.2
Name: nodezator
Version: 1.5.4
Summary: A generalist Python node editor
Author-email: Kennedy Richard <kennedy@kennedyrichard.com>
License: Unlicense
Project-URL: Homepage, https://nodezator.com
Project-URL: Source Code, https://github.com/IndieSmiths/nodezator
Project-URL: Forum, https://github.com/IndieSmiths/nodezator/discussions
Project-URL: User Manual, https://manual.nodezator.com
Project-URL: Bug Tracker, https://github.com/IndieSmiths/nodezator/issues
Project-URL: Donate, https://indiesmiths.com/donate
Keywords: gui,desktop,application,pygame,pygame-ce,graph,graphs,nodes,node,editor
Classifier: License :: OSI Approved :: The Unlicense (Unlicense)
Classifier: Development Status :: 4 - Beta
Classifier: Programming Language :: Python :: 3
Classifier: Programming Language :: Python :: Implementation :: CPython
Classifier: Topic :: Software Development
Classifier: Topic :: Software Development :: Libraries :: pygame
Classifier: Topic :: Desktop Environment
Classifier: Topic :: Multimedia
Classifier: Topic :: Software Development :: User Interfaces
Classifier: Topic :: Software Development :: Code Generators
Classifier: Topic :: Artistic Software
Classifier: Topic :: Office/Business
Classifier: Topic :: Scientific/Engineering
Classifier: Intended Audience :: End Users/Desktop
Requires-Python: >=3.7
Requires-Dist: pygame-ce
Requires-Dist: numpy
